[{"cik": "1144215", "ticker_symbol": "AYI"}, {"cik": "886125", "ticker_symbol": "ALU"}, {"cik": "1018724", "ticker_symbol": "AMZN"}, {"cik": "1037868", "ticker_symbol": "AME"}, {"cik": "820313", "ticker_symbol": "APH"}, {"cik": "320193", "ticker_symbol": "AAPL"}, {"cik": "1034670", "ticker_symbol": "ALV"}, {"cik": "1441634", "ticker_symbol": "AVGO"}, {"cik": "8818", "ticker_symbol": "AVY"}, {"cik": "8858", "ticker_symbol": "AVT"}, {"cik": "808362", "ticker_symbol": "BHI"}, {"cik": "9389", "ticker_symbol": "BLL"}, {"cik": "10456", "ticker_symbol": "BAX"}, {"cik": "10795", "ticker_symbol": "BDX"}, {"cik": "886158", "ticker_symbol": "BBBY"}, {"cik": "12927", "ticker_symbol": "BA"}, {"cik": "908255", "ticker_symbol": "BWA"}, {"cik": "885725", "ticker_symbol": "BSX"}, {"cik": "14930", "ticker_symbol": "BC"}, {"cik": "837465", "ticker_symbol": "ELY"}, {"cik": "941548", "ticker_symbol": "CAM"}, {"cik": "790051", "ticker_symbol": "CSL"}, {"cik": "18230", "ticker_symbol": "CAT"}, {"cik": "93410", "ticker_symbol": "CVX"}, {"cik": "858877", "ticker_symbol": "CSCO"}, {"cik": "1116132", "ticker_symbol": "COH"}, {"cik": "24741", "ticker_symbol": "GLW"}, {"cik": "1219601", "ticker_symbol": "CCK"}, {"cik": "26172", "ticker_symbol": "CMI"}, {"cik": "313616", "ticker_symbol": "DHR"}, {"cik": "315189", "ticker_symbol": "DE"}, {"cik": "1521332", "ticker_symbol": "DLPH"}, {"cik": "790070", "ticker_symbol": "EMC"}, {"cik": "1551182", "ticker_symbol": "ETN"}, {"cik": "32604", "ticker_symbol": "EMR"}, {"cik": "0000895126", "ticker_symbol": "CHK"}, {"cik": "34088", "ticker_symbol": "XOM"}, {"cik": "1048695", "ticker_symbol": "FFIV"}, {"cik": "1135152", "ticker_symbol": "FTI"}, {"cik": "866374", "ticker_symbol": "FLEX"}, {"cik": "37996", "ticker_symbol": "F"}, {"cik": "39911", "ticker_symbol": "GPS"}, {"cik": "1121788", "ticker_symbol": "GRMN"}, {"cik": "40533", "ticker_symbol": "GD"}, {"cik": "40545", "ticker_symbol": "GE"}, {"cik": "1467858", "ticker_symbol": "GM"}, {"cik": "42582", "ticker_symbol": "GT"}, {"cik": "1408075", "ticker_symbol": "GPK"}, {"cik": "45012", "ticker_symbol": "HAL"}, {"cik": "1359841", "ticker_symbol": "HBI"}, {"cik": "793952", "ticker_symbol": "HOG"}, {"cik": "800459", "ticker_symbol": "HAR"}, {"cik": "46080", "ticker_symbol": "HAS"}, {"cik": "47217", "ticker_symbol": "HPQ"}, {"cik": "354950", "ticker_symbol": "HD"}, {"cik": "773840", "ticker_symbol": "HON"}, {"cik": "813762", "ticker_symbol": "IEP"}, {"cik": "49826", "ticker_symbol": "ITW"}, {"cik": "1466258", "ticker_symbol": "IR"}, {"cik": "50863", "ticker_symbol": "INTC"}, {"cik": "51143", "ticker_symbol": "IBM"}, {"cik": "895655", "ticker_symbol": "JAH"}, {"cik": "200406", "ticker_symbol": "JNJ"}, {"cik": "53669", "ticker_symbol": "JCI"}, {"cik": "1043604", "ticker_symbol": "JNPR"}, {"cik": "842162", "ticker_symbol": "LEA"}, {"cik": "58492", "ticker_symbol": "LEG"}, {"cik": "936468", "ticker_symbol": "LMT"}, {"cik": "60667", "ticker_symbol": "LOW"}, {"cik": "857471", "ticker_symbol": "LUX"}, {"cik": "63276", "ticker_symbol": "MAT"}, {"cik": "1613103", "ticker_symbol": "MDT"}, {"cik": "1530721", "ticker_symbol": "KORS"}, {"cik": "723125", "ticker_symbol": "MU"}, {"cik": "789019", "ticker_symbol": "MSFT"}, {"cik": "851968", "ticker_symbol": "MHK"}, {"cik": "68505", "ticker_symbol": "MSI"}, {"cik": "1413447", "ticker_symbol": "NXPI"}, {"cik": "1021860", "ticker_symbol": "NOV"}, {"cik": "1078207", "ticker_symbol": "NLS"}, {"cik": "814453", "ticker_symbol": "NWL"}, {"cik": "320187", "ticker_symbol": "NKE"}, {"cik": "1133421", "ticker_symbol": "NOC"}, {"cik": "75362", "ticker_symbol": "PCAR"}, {"cik": "1327567", "ticker_symbol": "PANW"}, {"cik": "76334", "ticker_symbol": "PH"}, {"cik": "1413329", "ticker_symbol": "PM"}, {"cik": "931015", "ticker_symbol": "PII"}, {"cik": "80424", "ticker_symbol": "PG"}, {"cik": "804328", "ticker_symbol": "QCOM"}, {"cik": "1037038", "ticker_symbol": "RL"}, {"cik": "82166", "ticker_symbol": "RAVN"}, {"cik": "1047122", "ticker_symbol": "RTN"}, {"cik": "1024478", "ticker_symbol": "ROK"}, {"cik": "882835", "ticker_symbol": "ROP"}, {"cik": "745732", "ticker_symbol": "ROST"}, {"cik": "1000180", "ticker_symbol": "SNDK"}, {"cik": "87347", "ticker_symbol": "SLB"}, {"cik": "1137789", "ticker_symbol": "STX"}, {"cik": "1012100", "ticker_symbol": "SEE"}, {"cik": "1477294", "ticker_symbol": "ST"}, {"cik": "1092796", "ticker_symbol": "SWHC"}, {"cik": "91767", "ticker_symbol": "SON"}, {"cik": "203077", "ticker_symbol": "STJ"}, {"cik": "93556", "ticker_symbol": "SWK"}, {"cik": "310764", "ticker_symbol": "SYK"}, {"cik": "95029", "ticker_symbol": "RGR"}, {"cik": "1385157", "ticker_symbol": "TEL"}, {"cik": "109198", "ticker_symbol": "TJX"}, {"cik": "1318605", "ticker_symbol": "TSLA"}, {"cik": "97476", "ticker_symbol": "TXN"}, {"cik": "730263", "ticker_symbol": "THO"}, {"cik": "98246", "ticker_symbol": "TIF"}, {"cik": "1094517", "ticker_symbol": "TM"}, {"cik": "864749", "ticker_symbol": "TRMB"}, {"cik": "1336917", "ticker_symbol": "UA"}, {"cik": "101829", "ticker_symbol": "UTX"}, {"cik": "103379", "ticker_symbol": "VFC"}, {"cik": "732712", "ticker_symbol": "VZ"}, {"cik": "104169", "ticker_symbol": "WMT"}, {"cik": "1001039", "ticker_symbol": "DIS"}, {"cik": "1603923", "ticker_symbol": "WFT"}, {"cik": "106040", "ticker_symbol": "WDC"}, {"cik": "106640", "ticker_symbol": "WHR"}, {"cik": "0000034088", "ticker_symbol": "XOM"}, {"cik": "937966", "ticker_symbol": "ASML"}]